nexium_api_client/__init__.py
nexium_api_client/api_client.py
nexium_api_client/api_response.py
nexium_api_client/configuration.py
nexium_api_client/exceptions.py
nexium_api_client/py.typed
nexium_api_client/rest.py
nexium_api_client/api/__init__.py
nexium_api_client/api/parser_api.py
nexium_api_client/api/users_api.py
nexium_api_client/models/__init__.py
nexium_api_client/models/accordance_status.py
nexium_api_client/models/check_disciplinary_action.py
nexium_api_client/models/check_result.py
nexium_api_client/models/check_state.py
nexium_api_client/models/check_upsert_request.py
nexium_api_client/models/http_validation_error.py
nexium_api_client/models/insurance_upsert_request.py
nexium_api_client/models/legal_form.py
nexium_api_client/models/member_status.py
nexium_api_client/models/organization_schema.py
nexium_api_client/models/registry.py
nexium_api_client/models/response_data_user_response.py
nexium_api_client/models/sro_member_upsert_request.py
nexium_api_client/models/sro_upsert_request.py
nexium_api_client/models/user_response.py
nexium_api_client/models/validation_error.py
nexium_api_client/models/validation_error_loc_inner.py
openapi_client/__init__.py
openapi_client/api_client.py
openapi_client/api_response.py
openapi_client/configuration.py
openapi_client/exceptions.py
openapi_client/py.typed
openapi_client/rest.py
openapi_client/api/__init__.py
openapi_client/api/parser_api.py
openapi_client/api/users_api.py
openapi_client/models/__init__.py
openapi_client/models/accordance_status.py
openapi_client/models/check_disciplinary_action.py
openapi_client/models/check_result.py
openapi_client/models/check_state.py
openapi_client/models/check_upsert_request.py
openapi_client/models/http_validation_error.py
openapi_client/models/insurance_upsert_request.py
openapi_client/models/legal_form.py
openapi_client/models/member_status.py
openapi_client/models/organization_schema.py
openapi_client/models/registry.py
openapi_client/models/response_data_user_response.py
sromaster-0.1.36.dist-info/METADATA
sromaster-0.1.36.dist-info/WHEEL
sromaster-0.1.36.dist-info/top_level.txt
sromaster-0.1.36.dist-info/RECORD
